torch_audiomentations/__init__.py
torch_audiomentations/augmentations/__init__.py
torch_audiomentations/augmentations/background_noise.py
torch_audiomentations/augmentations/band_pass_filter.py
torch_audiomentations/augmentations/band_stop_filter.py
torch_audiomentations/augmentations/colored_noise.py
torch_audiomentations/augmentations/gain.py
torch_audiomentations/augmentations/high_pass_filter.py
torch_audiomentations/augmentations/identity.py
torch_audiomentations/augmentations/impulse_response.py
torch_audiomentations/augmentations/low_pass_filter.py
torch_audiomentations/augmentations/mix.py
torch_audiomentations/augmentations/padding.py
torch_audiomentations/augmentations/peak_normalization.py
torch_audiomentations/augmentations/pitch_shift.py
torch_audiomentations/augmentations/polarity_inversion.py
torch_audiomentations/augmentations/random_crop.py
torch_audiomentations/augmentations/shift.py
torch_audiomentations/augmentations/shuffle_channels.py
torch_audiomentations/augmentations/splice_out.py
torch_audiomentations/augmentations/time_inversion.py
torch_audiomentations/core/__init__.py
torch_audiomentations/core/composition.py
torch_audiomentations/core/transforms_interface.py
torch_audiomentations/utils/__init__.py
torch_audiomentations/utils/config.py
torch_audiomentations/utils/convolution.py
torch_audiomentations/utils/dsp.py
torch_audiomentations/utils/fft.py
torch_audiomentations/utils/file.py
torch_audiomentations/utils/io.py
torch_audiomentations/utils/mel_scale.py
torch_audiomentations/utils/multichannel.py
torch_audiomentations/utils/object_dict.py
torch_audiomentations-0.12.0.dist-info/LICENSE
torch_audiomentations-0.12.0.dist-info/METADATA
torch_audiomentations-0.12.0.dist-info/WHEEL
torch_audiomentations-0.12.0.dist-info/top_level.txt
torch_audiomentations-0.12.0.dist-info/RECORD
