Metadata-Version: 2.1
Name: torch-audiomentations
Version: 0.12.0
Summary: A Pytorch library for audio data augmentation. Inspired by audiomentations. Useful for deep learning.
Home-page: https://github.com/asteroid-team/torch-audiomentations
Author: Iver Jordal
License: MIT
Classifier: Programming Language :: Python :: 3
Classifier: License :: OSI Approved :: MIT License
Classifier: Operating System :: OS Independent
Classifier: Development Status :: 3 - Alpha
Classifier: Intended Audience :: Developers
Classifier: Intended Audience :: Science/Research
Classifier: Topic :: Multimedia
Classifier: Topic :: Multimedia :: Sound/Audio
Classifier: Topic :: Scientific/Engineering
Classifier: Topic :: Scientific/Engineering :: Artificial Intelligence
Requires-Python: >=3.6
License-File: LICENSE
Requires-Dist: julius<0.3,>=0.2.3
Requires-Dist: torch>=1.7.0
Requires-Dist: torchaudio>=0.9.0
Requires-Dist: torch-pitch-shift>=1.2.2
Provides-Extra: extras
Requires-Dist: PyYAML; extra == "extras"
